deltascope/__init__.py
deltascope/alignment.py
deltascope/mpTransformation.py
deltascope/new.py
deltascope/process_after_gui.py
deltascope/test_transform.py
deltascope-0.2.6.dist-info/LICENSE.md
deltascope-0.2.6.dist-info/METADATA
deltascope-0.2.6.dist-info/WHEEL
deltascope-0.2.6.dist-info/top_level.txt
deltascope-0.2.6.dist-info/RECORD
