Metadata-Version: 2.1
Name: deltascope
Version: 0.2.6
Summary: Python package to quantify biological structure
Home-page: https://github.com/msschwartz21/deltascope
Author: Morgan Schwartz
Author-email: msschwartz21@gmail.com
License: GNU GPL
Keywords: biology image analysis quantification
Platform: UNKNOWN
Classifier: License :: OSI Approved :: GNU General Public License (GPL)
Classifier: Programming Language :: Python :: 3.7
Requires-Dist: numpy
Requires-Dist: h5py
Requires-Dist: matplotlib
Requires-Dist: pandas
Requires-Dist: scipy
Requires-Dist: scikit-learn
Requires-Dist: scikit-image
Requires-Dist: tqdm
